{
    "1": {
        "1": {
            "221": "12",
            "50": "12",
            "90": "19"
        },
        "2": {
            "149": "2",
            "157": "12"
        },
        "3": {
            "139": "2",
            "70": "19",
            "9": "2"
        },
        "4": {
            "1": "15",
            "112": "15",
            "38": "12"
        },
        "5": {
            "102": "15",
            "194": "2",
            "213": "15"
        },
        "6": {
            "185": "19",
            "60": "19",
            "79": "19"
        },
        "7": {
            "126": "19",
            "237": "19",
            "27": "19"
        },
        "8": {
            "169": "19",
            "203": "12",
            "229": "12"
        },
        "9": {
            "177": "15",
            "18": "15"
        }
    },
    "2": {
        "1": {
            "221": "16",
            "50": "16",
            "90": "16"
        },
        "2": {
            "149": "0",
            "157": "0"
        },
        "3": {
            "139": "20",
            "70": "20",
            "9": "20"
        },
        "4": {
            "1": "0",
            "112": "20",
            "38": "20"
        },
        "5": {
            "102": "13",
            "194": "13",
            "213": "20"
        },
        "6": {
            "185": "16",
            "60": "16",
            "79": "16"
        },
        "7": {
            "126": "13",
            "237": "13",
            "27": "13"
        },
        "8": {
            "169": "13",
            "203": "13",
            "229": "16"
        },
        "9": {
            "177": "20",
            "18": "20"
        }
    },
    "3": {
        "1": {
            "221": "18",
            "50": "18",
            "90": "18"
        },
        "2": {
            "149": "18",
            "157": "18"
        },
        "3": {
            "139": "3",
            "70": "18",
            "9": "3"
        },
        "4": {
            "1": "18",
            "112": "18",
            "38": "18"
        },
        "5": {
            "102": "3",
            "194": "3",
            "213": "3"
        },
        "6": {
            "185": "18",
            "60": "18",
            "79": "18"
        },
        "7": {
            "126": "3",
            "237": "3",
            "27": "3"
        },
        "8": {
            "169": "18",
            "203": "18",
            "229": "18"
        },
        "9": {
            "177": "3",
            "18": "3"
        }
    },
    "4": {
        "1": {
            "221": "4",
            "50": "4",
            "90": "4"
        },
        "2": {
            "149": "8",
            "157": "8",
            "61": "4"
        },
        "3": {
            "139": "11",
            "70": "4",
            "9": "4"
        },
        "4": {
            "1": "4",
            "112": "4",
            "38": "4"
        },
        "5": {
            "102": "8",
            "194": "8",
            "213": "8"
        },
        "6": {
            "230": "4",
            "79": "17"
        },
        "7": {
            "126": "11",
            "237": "11",
            "27": "11"
        },
        "8": {
            "169": "17",
            "186": "11",
            "203": "11"
        },
        "9": {
            "177": "17",
            "18": "17"
        }
    },
    "5": {
        "1": {
            "221": "16",
            "50": "16",
            "90": "16"
        },
        "2": {
            "149": "12",
            "157": "12",
            "61": "12"
        },
        "3": {
            "139": "7",
            "70": "7",
            "9": "7"
        },
        "4": {
            "1": "7",
            "112": "7",
            "38": "12"
        },
        "5": {
            "102": "15",
            "194": "15",
            "213": "15"
        },
        "6": {
            "230": "7",
            "79": "7"
        },
        "7": {
            "126": "15",
            "237": "15",
            "27": "15"
        },
        "8": {
            "169": "15",
            "186": "16",
            "203": "16"
        },
        "9": {
            "177": "16",
            "18": "16"
        }
    },
    "6": {
        "1": {
            "221": "6",
            "50": "6",
            "90": "6"
        },
        "2": {
            "149": "20",
            "157": "20",
            "61": "20"
        },
        "3": {
            "139": "20",
            "70": "20",
            "9": "20"
        },
        "4": {
            "1": "20",
            "112": "20",
            "38": "20"
        },
        "5": {
            "102": "6",
            "194": "6",
            "213": "6"
        },
        "6": {
            "230": "6",
            "79": "6"
        },
        "7": {
            "126": "6",
            "237": "6",
            "27": "6"
        },
        "8": {
            "169": "20",
            "186": "20",
            "203": "20"
        },
        "9": {
            "177": "6",
            "18": "6"
        }
    },
    "7": {
        "1": {
            "221": "10",
            "71": "10",
            "90": "10"
        },
        "2": {
            "149": "10",
            "157": "10",
            "61": "10"
        },
        "3": {
            "139": "10",
            "9": "10"
        },
        "4": {
            "1": "10",
            "112": "1",
            "38": "10"
        },
        "5": {
            "102": "18",
            "194": "18",
            "213": "18"
        },
        "6": {
            "230": "1",
            "51": "1",
            "79": "1"
        },
        "7": {
            "126": "1",
            "237": "1",
            "27": "1"
        },
        "8": {
            "169": "18",
            "186": "18"
        },
        "9": {
            "177": "18",
            "18": "18",
            "204": "18"
        }
    },
    "8": {
        "1": {
            "221": "3",
            "71": "3",
            "90": "3"
        },
        "2": {
            "149": "8",
            "157": "8",
            "61": "8"
        },
        "3": {
            "139": "3",
            "9": "3"
        },
        "4": {
            "1": "8",
            "112": "8",
            "38": "8"
        },
        "5": {
            "102": "8",
            "194": "8",
            "213": "8"
        },
        "6": {
            "230": "14",
            "51": "14",
            "79": "14"
        },
        "7": {
            "126": "8",
            "237": "8",
            "27": "8"
        },
        "8": {
            "169": "14",
            "186": "14"
        },
        "9": {
            "177": "14",
            "18": "14",
            "204": "14"
        }
    },
    "9": {
        "1": {
            "221": "11",
            "71": "11",
            "90": "11"
        },
        "2": {
            "149": "20",
            "157": "20",
            "61": "20"
        },
        "3": {
            "139": "11",
            "9": "11"
        },
        "4": {
            "1": "15",
            "112": "15",
            "38": "15"
        },
        "5": {
            "102": "11",
            "194": "11",
            "213": "11"
        },
        "6": {
            "230": "11",
            "51": "11",
            "79": "11"
        },
        "7": {
            "126": "15",
            "237": "15",
            "27": "15"
        },
        "8": {
            "169": "15",
            "186": "15"
        },
        "9": {
            "177": "20",
            "18": "20",
            "204": "20"
        }
    },
    "10": {
        "1": {
            "221": "13",
            "71": "13",
            "90": "13"
        },
        "10": {
            "158": "1"
        },
        "2": {
            "149": "17",
            "238": "17",
            "61": "17"
        },
        "3": {
            "139": "13",
            "39": "17",
            "9": "13"
        },
        "4": {
            "1": "1",
            "103": "1",
            "127": "2"
        },
        "5": {
            "194": "13",
            "213": "13",
            "80": "13"
        },
        "6": {
            "230": "1",
            "51": "1"
        },
        "7": {
            "27": "2"
        },
        "8": {
            "113": "2",
            "169": "13",
            "186": "13"
        },
        "9": {
            "177": "17",
            "18": "17",
            "204": "17"
        }
    },
    "11": {
        "1": {
            "221": "5",
            "71": "5",
            "90": "5"
        },
        "10": {
            "158": "14"
        },
        "2": {
            "149": "5",
            "238": "5",
            "61": "5"
        },
        "3": {
            "139": "7",
            "39": "7",
            "9": "7"
        },
        "4": {
            "1": "7",
            "103": "7",
            "127": "5"
        },
        "5": {
            "194": "7",
            "213": "7",
            "80": "7"
        },
        "6": {
            "230": "14",
            "51": "14"
        },
        "7": {
            "27": "19"
        },
        "8": {
            "113": "14",
            "169": "14",
            "186": "14"
        },
        "9": {
            "177": "5",
            "18": "5",
            "204": "5"
        }
    },
    "12": {
        "1": {
            "221": "11",
            "71": "11",
            "90": "11"
        },
        "10": {
            "158": "15"
        },
        "2": {
            "149": "20",
            "238": "20",
            "61": "20"
        },
        "3": {
            "139": "11",
            "39": "11",
            "9": "11"
        },
        "4": {
            "1": "15",
            "103": "15",
            "127": "15"
        },
        "5": {
            "194": "20",
            "213": "20",
            "80": "20"
        },
        "6": {
            "230": "11",
            "51": "11"
        },
        "7": {
            "27": "11"
        },
        "8": {
            "113": "20",
            "169": "20",
            "186": "20"
        },
        "9": {
            "177": "15",
            "18": "15",
            "204": "15"
        }
    },
    "13": {
        "1": {
            "221": "12",
            "71": "12",
            "91": "0"
        },
        "10": {
            "158": "17",
            "28": "17"
        },
        "2": {
            "149": "17",
            "238": "17",
            "61": "17"
        },
        "3": {
            "40": "12"
        },
        "4": {
            "103": "12",
            "127": "12",
            "2": "12"
        },
        "5": {
            "194": "8",
            "213": "8",
            "80": "8"
        },
        "6": {
            "230": "8",
            "51": "8"
        },
        "7": {
            "10": "8",
            "140": "8"
        },
        "8": {
            "113": "17",
            "169": "17",
            "186": "17"
        },
        "9": {
            "177": "8",
            "18": "8",
            "204": "8"
        }
    },
    "14": {
        "1": {
            "221": "18",
            "71": "10",
            "91": "18"
        },
        "10": {
            "158": "6",
            "28": "6"
        },
        "2": {
            "149": "10",
            "238": "10",
            "61": "10"
        },
        "3": {
            "40": "9"
        },
        "4": {
            "103": "6",
            "127": "18",
            "2": "18"
        },
        "5": {
            "194": "6",
            "213": "6",
            "80": "6"
        },
        "6": {
            "230": "6",
            "51": "6"
        },
        "7": {
            "10": "9",
            "140": "10"
        },
        "8": {
            "113": "10",
            "169": "10",
            "186": "10"
        },
        "9": {
            "177": "6",
            "18": "6",
            "204": "6"
        }
    },
    "15": {
        "1": {
            "221": "16",
            "71": "16",
            "91": "4"
        },
        "10": {
            "158": "3",
            "28": "3"
        },
        "2": {
            "149": "4",
            "238": "4",
            "61": "4"
        },
        "3": {
            "40": "4"
        },
        "4": {
            "103": "4",
            "127": "4",
            "2": "4"
        },
        "5": {
            "194": "3",
            "213": "3",
            "80": "3"
        },
        "6": {
            "230": "3",
            "51": "3"
        },
        "7": {
            "10": "4",
            "140": "4"
        },
        "8": {
            "113": "4",
            "169": "4",
            "186": "4"
        },
        "9": {
            "177": "3",
            "18": "3",
            "204": "3"
        }
    },
    "16": {
        "10": {
            "28": "20",
            "41": "20",
            "72": "20"
        },
        "2": {
            "178": "20",
            "238": "20",
            "61": "20"
        },
        "3": {
            "170": "2",
            "19": "2",
            "92": "14"
        },
        "4": {
            "103": "17",
            "2": "17",
            "52": "17"
        },
        "5": {
            "128": "17",
            "214": "17",
            "80": "17"
        },
        "6": {
            "150": "17",
            "159": "14",
            "230": "14"
        },
        "7": {
            "10": "14",
            "140": "14",
            "222": "14"
        },
        "8": {
            "113": "20",
            "186": "20",
            "195": "20"
        },
        "9": {
            "204": "14"
        }
    },
    "17": {
        "10": {
            "28": "19",
            "41": "19",
            "72": "19"
        },
        "2": {
            "178": "1",
            "238": "19",
            "61": "1"
        },
        "3": {
            "170": "1",
            "19": "15",
            "92": "15"
        },
        "4": {
            "103": "0",
            "2": "19",
            "52": "19"
        },
        "5": {
            "128": "0",
            "214": "0",
            "80": "0"
        },
        "6": {
            "150": "19",
            "159": "19",
            "230": "0"
        },
        "7": {
            "10": "0",
            "140": "0",
            "222": "1"
        },
        "8": {
            "113": "19",
            "186": "19",
            "195": "19"
        },
        "9": {
            "204": "15"
        }
    },
    "18": {
        "10": {
            "28": "9",
            "41": "9",
            "72": "16"
        },
        "2": {
            "178": "10",
            "238": "10",
            "61": "10"
        },
        "3": {
            "170": "16",
            "19": "16",
            "92": "16"
        },
        "4": {
            "103": "10",
            "2": "10",
            "52": "10"
        },
        "5": {
            "128": "10",
            "214": "10",
            "80": "10"
        },
        "6": {
            "150": "10",
            "159": "10",
            "230": "10"
        },
        "7": {
            "10": "9",
            "140": "9",
            "222": "9"
        },
        "8": {
            "113": "16",
            "186": "16",
            "195": "16"
        },
        "9": {
            "204": "9"
        }
    },
    "19": {
        "1": {
            "141": "11",
            "205": "11"
        },
        "10": {
            "28": "7",
            "41": "7",
            "93": "7"
        },
        "2": {
            "178": "11",
            "238": "11",
            "81": "11"
        },
        "3": {
            "170": "2",
            "187": "2",
            "19": "18"
        },
        "4": {
            "103": "2",
            "114": "7",
            "52": "18"
        },
        "5": {
            "128": "18",
            "214": "18"
        },
        "6": {
            "150": "18",
            "159": "2",
            "231": "2"
        },
        "7": {
            "10": "7",
            "222": "7",
            "62": "18"
        },
        "8": {
            "195": "11",
            "3": "18",
            "72": "18"
        }
    },
    "20": {
        "1": {
            "141": "12",
            "205": "12"
        },
        "10": {
            "28": "19",
            "41": "19",
            "93": "19"
        },
        "2": {
            "178": "19",
            "238": "13",
            "81": "19"
        },
        "3": {
            "170": "13",
            "187": "13",
            "19": "13"
        },
        "4": {
            "103": "19",
            "114": "14",
            "52": "19"
        },
        "5": {
            "128": "12",
            "214": "12"
        },
        "6": {
            "150": "14",
            "159": "14",
            "231": "14"
        },
        "7": {
            "10": "14",
            "222": "14",
            "62": "14"
        },
        "8": {
            "195": "12",
            "3": "12",
            "72": "12"
        }
    },
    "21": {
        "1": {
            "141": "3",
            "205": "3"
        },
        "10": {
            "28": "6",
            "41": "6",
            "93": "6"
        },
        "2": {
            "178": "6",
            "238": "6",
            "81": "6"
        },
        "3": {
            "170": "3",
            "187": "6",
            "19": "6"
        },
        "4": {
            "103": "6",
            "114": "6",
            "52": "6"
        },
        "5": {
            "128": "20",
            "214": "20"
        },
        "6": {
            "150": "6",
            "159": "6",
            "231": "6"
        },
        "7": {
            "10": "3",
            "222": "3",
            "62": "3"
        },
        "8": {
            "195": "3",
            "3": "3",
            "72": "3"
        }
    },
    "22": {
        "1": {
            "160": "1",
            "171": "4",
            "205": "1"
        },
        "10": {
            "28": "17",
            "41": "17"
        },
        "2": {
            "178": "7",
            "238": "1",
            "81": "1"
        },
        "3": {
            "187": "17",
            "19": "17",
            "94": "17"
        },
        "4": {
            "114": "7",
            "129": "7",
            "53": "7"
        },
        "5": {
            "104": "4",
            "142": "4"
        },
        "6": {
            "150": "17",
            "214": "17",
            "231": "17"
        },
        "7": {
            "10": "4",
            "222": "4",
            "62": "4"
        },
        "8": {
            "195": "7",
            "3": "7",
            "72": "7"
        }
    },
    "23": {
        "1": {
            "160": "14",
            "171": "14",
            "205": "14"
        },
        "10": {
            "28": "0",
            "41": "0"
        },
        "2": {
            "178": "0",
            "238": "13",
            "81": "13"
        },
        "3": {
            "187": "18",
            "19": "18",
            "94": "0"
        },
        "4": {
            "114": "14",
            "129": "13",
            "53": "13"
        },
        "5": {
            "104": "13",
            "142": "0"
        },
        "6": {
            "150": "18",
            "214": "18",
            "231": "18"
        },
        "7": {
            "10": "18",
            "222": "18",
            "62": "18"
        },
        "8": {
            "195": "18",
            "3": "18",
            "72": "18"
        }
    },
    "24": {
        "1": {
            "160": "19",
            "171": "19",
            "205": "19"
        },
        "10": {
            "28": "9",
            "41": "9"
        },
        "2": {
            "178": "19",
            "238": "19",
            "81": "19"
        },
        "3": {
            "187": "2",
            "19": "2",
            "94": "2"
        },
        "4": {
            "114": "9",
            "129": "9",
            "53": "9"
        },
        "5": {
            "104": "2",
            "142": "2"
        },
        "6": {
            "150": "2",
            "214": "2",
            "231": "2"
        },
        "7": {
            "10": "9",
            "222": "9",
            "62": "9"
        },
        "8": {
            "195": "19",
            "3": "19",
            "72": "19"
        }
    },
    "25": {
        "1": {
            "171": "12",
            "205": "12"
        },
        "10": {
            "41": "11"
        },
        "2": {
            "178": "11",
            "81": "11"
        },
        "3": {
            "11": "17",
            "20": "17",
            "94": "17"
        },
        "4": {
            "114": "11",
            "130": "17",
            "239": "11"
        },
        "5": {
            "104": "3",
            "142": "3"
        },
        "6": {
            "150": "11",
            "214": "11",
            "231": "11"
        },
        "7": {
            "222": "3",
            "54": "12",
            "62": "3"
        },
        "8": {
            "195": "12",
            "3": "12",
            "72": "12"
        },
        "9": {
            "161": "3",
            "188": "12",
            "29": "17"
        }
    },
    "26": {
        "1": {
            "171": "14",
            "205": "14"
        },
        "10": {
            "41": "7"
        },
        "2": {
            "178": "6",
            "81": "6"
        },
        "3": {
            "11": "14",
            "20": "14",
            "94": "14"
        },
        "4": {
            "114": "6",
            "130": "6",
            "239": "18"
        },
        "5": {
            "104": "18",
            "142": "6"
        },
        "6": {
            "150": "6",
            "214": "6",
            "231": "6"
        },
        "7": {
            "222": "14",
            "54": "14",
            "62": "14"
        },
        "8": {
            "195": "7",
            "3": "7",
            "72": "7"
        },
        "9": {
            "161": "18",
            "188": "18",
            "29": "18"
        }
    },
    "27": {
        "1": {
            "171": "16",
            "205": "16"
        },
        "10": {
            "41": "9"
        },
        "2": {
            "178": "16",
            "81": "16"
        },
        "3": {
            "11": "9",
            "20": "9",
            "94": "9"
        },
        "4": {
            "114": "9",
            "130": "9",
            "239": "9"
        },
        "5": {
            "104": "9",
            "142": "9"
        },
        "6": {
            "150": "2",
            "214": "2",
            "231": "2"
        },
        "7": {
            "222": "9",
            "54": "9",
            "62": "9"
        },
        "8": {
            "195": "16",
            "3": "16",
            "72": "16"
        },
        "9": {
            "161": "16",
            "188": "16",
            "29": "16"
        }
    },
    "28": {
        "1": {
            "171": "13",
            "196": "17",
            "205": "13"
        },
        "2": {
            "223": "13",
            "73": "0"
        },
        "3": {
            "11": "17",
            "21": "17",
            "94": "17"
        },
        "4": {
            "239": "8",
            "42": "8",
            "63": "0"
        },
        "5": {
            "104": "8",
            "142": "8",
            "82": "8"
        },
        "6": {
            "179": "8",
            "214": "8",
            "231": "8"
        },
        "7": {
            "115": "13",
            "54": "13"
        },
        "8": {
            "131": "13",
            "151": "13",
            "3": "13"
        },
        "9": {
            "161": "17",
            "188": "17",
            "29": "17"
        }
    },
    "29": {
        "1": {
            "171": "4",
            "196": "10",
            "205": "4"
        },
        "2": {
            "223": "4",
            "73": "11"
        },
        "3": {
            "11": "11",
            "21": "11",
            "94": "11"
        },
        "4": {
            "239": "10",
            "42": "10",
            "63": "10"
        },
        "5": {
            "104": "4",
            "142": "4",
            "82": "4"
        },
        "6": {
            "179": "20",
            "214": "11",
            "231": "11"
        },
        "7": {
            "115": "20",
            "54": "20"
        },
        "8": {
            "131": "20",
            "151": "20",
            "3": "4"
        },
        "9": {
            "161": "4",
            "188": "4",
            "29": "4"
        }
    },
    "30": {
        "1": {
            "171": "12",
            "196": "12",
            "205": "12"
        },
        "2": {
            "223": "5",
            "73": "5"
        },
        "3": {
            "11": "5",
            "21": "5",
            "94": "5"
        },
        "4": {
            "239": "12",
            "42": "12",
            "63": "12"
        },
        "5": {
            "104": "5",
            "142": "5",
            "82": "5"
        },
        "6": {
            "179": "12",
            "214": "12",
            "231": "12"
        },
        "7": {
            "115": "5",
            "54": "5"
        },
        "8": {
            "131": "5",
            "151": "5",
            "3": "5"
        },
        "9": {
            "161": "12",
            "188": "12",
            "29": "12"
        }
    },
    "31": {
        "1": {
            "196": "7",
            "215": "7"
        },
        "2": {
            "223": "19",
            "43": "19",
            "73": "2"
        },
        "3": {
            "172": "19",
            "21": "19",
            "94": "19"
        },
        "4": {
            "239": "1",
            "30": "1",
            "64": "7"
        },
        "5": {
            "104": "19",
            "142": "19",
            "82": "19"
        },
        "6": {
            "11": "1",
            "179": "19",
            "231": "1"
        },
        "7": {
            "206": "19",
            "54": "19"
        },
        "8": {
            "131": "1",
            "151": "1",
            "3": "7"
        },
        "9": {
            "116": "2",
            "161": "2",
            "188": "2"
        }
    },
    "32": {
        "1": {
            "196": "9",
            "215": "9"
        },
        "2": {
            "223": "15",
            "43": "0",
            "73": "0"
        },
        "3": {
            "172": "0",
            "21": "0",
            "94": "0"
        },
        "4": {
            "239": "17",
            "30": "17",
            "64": "17"
        },
        "5": {
            "104": "9",
            "142": "9",
            "82": "9"
        },
        "6": {
            "11": "9",
            "179": "9",
            "231": "9"
        },
        "7": {
            "206": "17",
            "54": "17"
        },
        "8": {
            "131": "15",
            "151": "15",
            "3": "15"
        },
        "9": {
            "116": "15",
            "161": "15",
            "188": "15"
        }
    },
    "33": {
        "1": {
            "196": "3",
            "215": "3"
        },
        "2": {
            "223": "8",
            "43": "8",
            "73": "3"
        },
        "3": {
            "172": "3",
            "21": "3",
            "94": "3"
        },
        "4": {
            "239": "18",
            "30": "18",
            "64": "18"
        },
        "5": {
            "104": "8",
            "142": "8",
            "82": "8"
        },
        "6": {
            "11": "8",
            "179": "8",
            "231": "8"
        },
        "7": {
            "206": "3",
            "54": "8"
        },
        "8": {
            "131": "8",
            "151": "8",
            "3": "8"
        },
        "9": {
            "116": "3",
            "161": "3",
            "188": "3"
        }
    },
    "34": {
        "1": {
            "132": "10",
            "173": "10",
            "215": "10"
        },
        "10": {
            "31": "13",
            "4": "10"
        },
        "2": {
            "224": "5",
            "232": "5",
            "73": "5"
        },
        "3": {
            "197": "5",
            "21": "5",
            "94": "5"
        },
        "4": {
            "239": "16",
            "64": "16"
        },
        "5": {
            "104": "5",
            "142": "5",
            "82": "5"
        },
        "6": {
            "11": "13",
            "179": "13",
            "44": "13"
        },
        "7": {
            "206": "13",
            "54": "13"
        },
        "8": {
            "151": "13"
        },
        "9": {
            "116": "16",
            "161": "16",
            "188": "16"
        }
    },
    "35": {
        "1": {
            "132": "4",
            "173": "12",
            "215": "4"
        },
        "10": {
            "31": "12",
            "4": "12"
        },
        "2": {
            "224": "9",
            "232": "20",
            "73": "9"
        },
        "3": {
            "197": "9",
            "21": "9",
            "94": "9"
        },
        "4": {
            "239": "9",
            "64": "9"
        },
        "5": {
            "104": "4",
            "142": "4",
            "82": "4"
        },
        "6": {
            "11": "20",
            "179": "20",
            "44": "20"
        },
        "7": {
            "206": "20",
            "54": "20"
        },
        "8": {
            "151": "4"
        },
        "9": {
            "116": "4",
            "161": "4",
            "188": "4"
        }
    },
    "36": {
        "1": {
            "132": "2",
            "173": "2",
            "215": "2"
        },
        "10": {
            "31": "17",
            "4": "17"
        },
        "2": {
            "224": "7",
            "232": "7",
            "73": "7"
        },
        "3": {
            "197": "17",
            "21": "17",
            "94": "17"
        },
        "4": {
            "239": "7",
            "64": "7"
        },
        "5": {
            "104": "7",
            "142": "7",
            "82": "7"
        },
        "6": {
            "11": "7",
            "179": "7",
            "44": "7"
        },
        "7": {
            "206": "17",
            "54": "17"
        },
        "8": {
            "151": "7"
        },
        "9": {
            "116": "2",
            "161": "2",
            "188": "2"
        }
    },
    "37": {
        "1": {
            "132": "11",
            "173": "11",
            "215": "11"
        },
        "10": {
            "198": "19",
            "4": "19"
        },
        "2": {
            "224": "11",
            "232": "11",
            "73": "11"
        },
        "3": {
            "105": "13",
            "117": "8",
            "152": "13"
        },
        "4": {
            "239": "8",
            "95": "11"
        },
        "5": {
            "189": "19",
            "32": "19",
            "82": "19"
        },
        "6": {
            "11": "13",
            "180": "13",
            "44": "13"
        },
        "7": {
            "206": "13",
            "54": "13"
        },
        "8": {
            "22": "8"
        },
        "9": {
            "143": "8",
            "161": "8",
            "65": "8"
        }
    },
    "38": {
        "1": {
            "132": "0",
            "173": "15",
            "215": "15"
        },
        "10": {
            "198": "6",
            "4": "6"
        },
        "2": {
            "224": "15",
            "232": "15",
            "73": "6"
        },
        "3": {
            "105": "20",
            "117": "20",
            "152": "0"
        },
        "4": {
            "239": "6",
            "95": "6"
        },
        "5": {
            "189": "20",
            "32": "15",
            "82": "15"
        },
        "6": {
            "11": "20",
            "180": "20",
            "44": "20"
        },
        "7": {
            "206": "20",
            "54": "20"
        },
        "8": {
            "22": "0"
        },
        "9": {
            "143": "0",
            "161": "15",
            "65": "15"
        }
    },
    "39": {
        "1": {
            "132": "5",
            "173": "5",
            "215": "5"
        },
        "10": {
            "198": "18",
            "4": "18"
        },
        "2": {
            "224": "5",
            "232": "5",
            "73": "5"
        },
        "3": {
            "105": "18",
            "117": "18",
            "152": "18"
        },
        "4": {
            "239": "18",
            "95": "18"
        },
        "5": {
            "189": "5",
            "32": "5",
            "82": "5"
        },
        "6": {
            "11": "5",
            "180": "5",
            "44": "5"
        },
        "7": {
            "206": "16",
            "54": "16"
        },
        "8": {
            "22": "18"
        },
        "9": {
            "143": "18",
            "161": "18",
            "65": "18"
        }
    },
    "40": {
        "1": {
            "173": "11",
            "215": "11"
        },
        "10": {
            "12": "4",
            "198": "4",
            "33": "4"
        },
        "2": {
            "144": "10",
            "224": "11",
            "232": "11"
        },
        "3": {
            "105": "17",
            "152": "10",
            "240": "10"
        },
        "4": {
            "118": "11",
            "83": "11"
        },
        "5": {
            "189": "17",
            "4": "17",
            "45": "17"
        },
        "6": {
            "162": "4",
            "180": "17",
            "74": "4"
        },
        "7": {
            "133": "11",
            "206": "11"
        },
        "8": {
            "22": "17",
            "96": "17"
        },
        "9": {
            "55": "4",
            "65": "4"
        }
    },
    "41": {
        "1": {
            "173": "2",
            "215": "2"
        },
        "10": {
            "12": "2",
            "198": "2",
            "33": "1"
        },
        "2": {
            "144": "13",
            "224": "13",
            "232": "13"
        },
        "3": {
            "105": "1",
            "152": "2",
            "240": "1"
        },
        "4": {
            "118": "19",
            "83": "19"
        },
        "5": {
            "189": "19",
            "4": "19",
            "45": "19"
        },
        "6": {
            "162": "1",
            "180": "1",
            "74": "1"
        },
        "7": {
            "133": "13",
            "206": "13"
        },
        "8": {
            "22": "19",
            "96": "19"
        },
        "9": {
            "55": "19",
            "65": "19"
        }
    },
    "42": {
        "1": {
            "173": "9",
            "215": "9"
        },
        "10": {
            "12": "18",
            "198": "18",
            "33": "18"
        },
        "2": {
            "144": "9",
            "224": "9",
            "232": "9"
        },
        "3": {
            "105": "18",
            "152": "18",
            "240": "18"
        },
        "4": {
            "118": "20",
            "83": "20"
        },
        "5": {
            "189": "9",
            "4": "9",
            "45": "9"
        },
        "6": {
            "162": "20",
            "180": "20",
            "74": "20"
        },
        "7": {
            "133": "20",
            "206": "20"
        },
        "8": {
            "22": "18",
            "96": "18"
        },
        "9": {
            "55": "18",
            "65": "18"
        }
    },
    "43": {
        "1": {
            "106": "16",
            "173": "16",
            "215": "16"
        },
        "10": {
            "12": "7",
            "198": "7",
            "33": "7"
        },
        "2": {
            "144": "16",
            "224": "7",
            "232": "7"
        },
        "3": {
            "152": "7",
            "240": "7"
        },
        "4": {
            "118": "16",
            "163": "16",
            "83": "16"
        },
        "5": {
            "189": "8",
            "4": "8",
            "45": "8"
        },
        "6": {
            "74": "8"
        },
        "7": {
            "134": "12",
            "181": "8"
        },
        "8": {
            "22": "16",
            "96": "16"
        },
        "9": {
            "207": "12",
            "55": "12",
            "65": "12"
        }
    },
    "44": {
        "1": {
            "106": "5",
            "173": "5",
            "215": "5"
        },
        "10": {
            "12": "5",
            "198": "2",
            "33": "2"
        },
        "2": {
            "144": "5",
            "224": "5",
            "232": "5"
        },
        "3": {
            "152": "19",
            "240": "19"
        },
        "4": {
            "118": "19",
            "163": "19",
            "83": "19"
        },
        "5": {
            "189": "19",
            "4": "19",
            "45": "19"
        },
        "6": {
            "74": "5"
        },
        "7": {
            "134": "2",
            "181": "3"
        },
        "8": {
            "22": "19",
            "96": "19"
        },
        "9": {
            "207": "3",
            "55": "3",
            "65": "3"
        }
    },
    "45": {
        "1": {
            "106": "11",
            "173": "11",
            "215": "11"
        },
        "10": {
            "12": "4",
            "198": "4",
            "33": "4"
        },
        "2": {
            "144": "11",
            "224": "11",
            "232": "11"
        },
        "3": {
            "152": "11",
            "240": "11"
        },
        "4": {
            "118": "4",
            "163": "4",
            "83": "4"
        },
        "5": {
            "189": "4",
            "4": "4",
            "45": "4"
        },
        "6": {
            "74": "4"
        },
        "7": {
            "134": "11",
            "181": "11"
        },
        "8": {
            "22": "4",
            "96": "4"
        },
        "9": {
            "207": "4",
            "55": "4",
            "65": "4"
        }
    },
    "46": {
        "1": {
            "106": "17",
            "153": "17",
            "173": "17"
        },
        "10": {
            "33": "0"
        },
        "2": {
            "144": "17",
            "224": "17",
            "232": "17"
        },
        "3": {
            "240": "10",
            "56": "10",
            "84": "10"
        },
        "4": {
            "118": "17",
            "163": "17",
            "97": "0"
        },
        "5": {
            "189": "17",
            "45": "17"
        },
        "6": {
            "13": "17",
            "199": "10",
            "74": "17"
        },
        "7": {
            "134": "13",
            "181": "13"
        },
        "8": {
            "216": "13",
            "22": "13"
        },
        "9": {
            "208": "0",
            "5": "0",
            "65": "0"
        }
    },
    "47": {
        "1": {
            "106": "8",
            "153": "8",
            "173": "8"
        },
        "10": {
            "33": "19"
        },
        "2": {
            "144": "9",
            "224": "9",
            "232": "9"
        },
        "3": {
            "240": "5",
            "56": "9",
            "84": "5"
        },
        "4": {
            "118": "19",
            "163": "19",
            "97": "19"
        },
        "5": {
            "189": "9",
            "45": "9"
        },
        "6": {
            "13": "19",
            "199": "19",
            "74": "8"
        },
        "7": {
            "134": "8",
            "181": "8"
        },
        "8": {
            "216": "5",
            "22": "5"
        },
        "9": {
            "208": "19",
            "5": "9",
            "65": "19"
        }
    },
    "48": {
        "1": {
            "106": "14",
            "153": "14",
            "173": "14"
        },
        "10": {
            "33": "18"
        },
        "2": {
            "144": "14",
            "224": "14",
            "232": "14"
        },
        "3": {
            "240": "18",
            "56": "18",
            "84": "18"
        },
        "4": {
            "118": "14",
            "163": "14",
            "97": "14"
        },
        "5": {
            "189": "18",
            "45": "18"
        },
        "6": {
            "13": "18",
            "199": "18",
            "74": "18"
        },
        "7": {
            "134": "14",
            "181": "14"
        },
        "8": {
            "216": "14",
            "22": "14"
        },
        "9": {
            "208": "18",
            "5": "18",
            "65": "18"
        }
    },
    "49": {
        "1": {
            "106": "10",
            "153": "10"
        },
        "10": {
            "217": "10",
            "23": "10",
            "33": "0"
        },
        "2": {
            "144": "20",
            "190": "20",
            "85": "3"
        },
        "3": {
            "240": "0",
            "56": "3"
        },
        "4": {
            "163": "20",
            "209": "0",
            "98": "3"
        },
        "5": {
            "135": "20",
            "233": "20",
            "45": "20"
        },
        "6": {
            "13": "20",
            "199": "10",
            "74": "10"
        },
        "7": {
            "174": "0",
            "181": "0",
            "66": "0"
        },
        "9": {
            "119": "20",
            "225": "20",
            "5": "20"
        }
    },
    "50": {
        "1": {
            "106": "16",
            "153": "16"
        },
        "10": {
            "217": "19",
            "23": "11",
            "33": "19"
        },
        "2": {
            "144": "11",
            "190": "11",
            "85": "11"
        },
        "3": {
            "240": "15",
            "56": "15"
        },
        "4": {
            "163": "15",
            "209": "15",
            "98": "15"
        },
        "5": {
            "135": "16",
            "233": "16",
            "45": "16"
        },
        "6": {
            "13": "16",
            "199": "16",
            "74": "16"
        },
        "7": {
            "174": "16",
            "181": "16",
            "66": "16"
        },
        "9": {
            "119": "19",
            "225": "19",
            "5": "19"
        }
    },
    "51": {
        "1": {
            "106": "5",
            "153": "5"
        },
        "10": {
            "217": "18",
            "23": "18",
            "33": "18"
        },
        "2": {
            "144": "5",
            "190": "5",
            "85": "5"
        },
        "3": {
            "240": "5",
            "56": "5"
        },
        "4": {
            "163": "5",
            "209": "5",
            "98": "5"
        },
        "5": {
            "135": "18",
            "233": "18",
            "45": "18"
        },
        "6": {
            "13": "18",
            "199": "18",
            "74": "18"
        },
        "7": {
            "174": "5",
            "181": "5",
            "66": "5"
        },
        "9": {
            "119": "18",
            "225": "18",
            "5": "18"
        }
    },
    "52": {
        "1": {
            "191": "12",
            "34": "8"
        },
        "10": {
            "120": "9",
            "217": "12",
            "23": "9"
        },
        "2": {
            "144": "8",
            "46": "8",
            "85": "8"
        },
        "3": {
            "200": "17",
            "240": "17",
            "56": "17"
        },
        "4": {
            "163": "9",
            "209": "9",
            "98": "8"
        },
        "5": {
            "107": "17",
            "135": "17",
            "233": "17"
        },
        "6": {
            "13": "17",
            "74": "17"
        },
        "7": {
            "174": "12",
            "181": "12",
            "66": "12"
        },
        "9": {
            "154": "9",
            "225": "9",
            "5": "17"
        }
    },
    "53": {
        "1": {
            "191": "20",
            "34": "20"
        },
        "10": {
            "120": "2",
            "217": "15",
            "23": "15"
        },
        "2": {
            "144": "11",
            "46": "11",
            "85": "11"
        },
        "3": {
            "200": "15",
            "240": "15",
            "56": "15"
        },
        "4": {
            "163": "2",
            "209": "11",
            "98": "2"
        },
        "5": {
            "107": "20",
            "135": "20",
            "233": "2"
        },
        "6": {
            "13": "20",
            "74": "20"
        },
        "7": {
            "174": "20",
            "181": "20",
            "66": "20"
        },
        "9": {
            "154": "11",
            "225": "2",
            "5": "11"
        }
    },
    "54": {
        "1": {
            "191": "3",
            "34": "3"
        },
        "10": {
            "120": "16",
            "217": "16",
            "23": "16"
        },
        "2": {
            "144": "16",
            "46": "16",
            "85": "16"
        },
        "3": {
            "200": "3",
            "240": "3",
            "56": "3"
        },
        "4": {
            "163": "13",
            "209": "13",
            "98": "13"
        },
        "5": {
            "107": "16",
            "135": "16",
            "233": "16"
        },
        "6": {
            "13": "3",
            "74": "3"
        },
        "7": {
            "174": "16",
            "181": "16",
            "66": "16"
        },
        "9": {
            "154": "3",
            "225": "3",
            "5": "3"
        }
    },
    "55": {
        "1": {
            "191": "6",
            "226": "19",
            "34": "6"
        },
        "10": {
            "120": "9",
            "217": "9",
            "23": "9"
        },
        "2": {
            "155": "6",
            "46": "19",
            "75": "6"
        },
        "3": {
            "145": "9",
            "200": "19",
            "56": "9"
        },
        "4": {
            "163": "9",
            "209": "9",
            "86": "4"
        },
        "5": {
            "107": "6",
            "135": "6",
            "233": "6"
        },
        "6": {
            "13": "4",
            "241": "4",
            "6": "4"
        },
        "7": {
            "181": "4",
            "66": "4",
            "99": "4"
        },
        "8": {
            "175": "6"
        }
    },
    "56": {
        "1": {
            "191": "8",
            "226": "8",
            "34": "8"
        },
        "10": {
            "120": "8",
            "217": "8",
            "23": "8"
        },
        "2": {
            "155": "15",
            "46": "5",
            "75": "15"
        },
        "3": {
            "145": "18",
            "200": "18",
            "56": "18"
        },
        "4": {
            "163": "15",
            "209": "15",
            "86": "15"
        },
        "5": {
            "107": "18",
            "135": "18",
            "233": "18"
        },
        "6": {
            "13": "5",
            "241": "18",
            "6": "5"
        },
        "7": {
            "181": "5",
            "66": "5",
            "99": "5"
        },
        "8": {
            "175": "18"
        }
    },
    "57": {
        "1": {
            "191": "12",
            "226": "12",
            "34": "12"
        },
        "10": {
            "120": "12",
            "217": "12",
            "23": "12"
        },
        "2": {
            "155": "16",
            "46": "16",
            "75": "16"
        },
        "3": {
            "145": "16",
            "200": "16",
            "56": "16"
        },
        "4": {
            "163": "16",
            "209": "16",
            "86": "16"
        },
        "5": {
            "107": "16",
            "135": "16",
            "233": "16"
        },
        "6": {
            "13": "12",
            "241": "12",
            "6": "12"
        },
        "7": {
            "181": "12",
            "66": "12",
            "99": "12"
        },
        "8": {
            "175": "16"
        }
    },
    "58": {
        "1": {
            "191": "6",
            "226": "6"
        },
        "10": {
            "120": "7",
            "217": "7",
            "23": "7"
        },
        "2": {
            "155": "6",
            "46": "20",
            "75": "20"
        },
        "3": {
            "145": "9",
            "200": "9",
            "56": "9"
        },
        "4": {
            "182": "20",
            "209": "20",
            "86": "20"
        },
        "5": {
            "107": "6",
            "135": "6",
            "233": "6"
        },
        "6": {
            "241": "20",
            "35": "6",
            "6": "20"
        },
        "7": {
            "164": "9",
            "66": "7",
            "99": "7"
        },
        "8": {
            "14": "7",
            "175": "7"
        }
    },
    "59": {
        "1": {
            "191": "1",
            "226": "1"
        },
        "10": {
            "120": "3",
            "217": "13",
            "23": "13"
        },
        "2": {
            "155": "17",
            "46": "17",
            "75": "17"
        },
        "3": {
            "145": "13",
            "200": "13",
            "56": "13"
        },
        "4": {
            "182": "13",
            "209": "13",
            "86": "13"
        },
        "5": {
            "107": "3",
            "135": "17",
            "233": "3"
        },
        "6": {
            "241": "3",
            "35": "3",
            "6": "3"
        },
        "7": {
            "164": "1",
            "66": "1",
            "99": "1"
        },
        "8": {
            "14": "17",
            "175": "17"
        }
    },
    "60": {
        "1": {
            "191": "0",
            "226": "0"
        },
        "10": {
            "120": "15",
            "217": "15",
            "23": "15"
        },
        "2": {
            "155": "15",
            "46": "15",
            "75": "15"
        },
        "3": {
            "145": "16",
            "200": "16",
            "56": "16"
        },
        "4": {
            "182": "15",
            "209": "15",
            "86": "15"
        },
        "5": {
            "107": "16",
            "135": "16",
            "233": "16"
        },
        "6": {
            "241": "0",
            "35": "0",
            "6": "0"
        },
        "7": {
            "164": "16",
            "66": "16",
            "99": "16"
        },
        "8": {
            "14": "16",
            "175": "16"
        }
    },
    "61": {
        "1": {
            "191": "12",
            "67": "20",
            "76": "12"
        },
        "10": {
            "120": "12",
            "24": "12"
        },
        "2": {
            "155": "20",
            "165": "20",
            "46": "20"
        },
        "3": {
            "145": "10",
            "200": "10",
            "57": "10"
        },
        "4": {
            "182": "7",
            "209": "7",
            "227": "7"
        },
        "5": {
            "107": "7",
            "135": "7",
            "233": "7"
        },
        "6": {
            "241": "20",
            "35": "20",
            "6": "20"
        },
        "7": {
            "15": "10",
            "87": "10",
            "99": "10"
        },
        "8": {
            "175": "10",
            "218": "10"
        }
    },
    "62": {
        "1": {
            "191": "14",
            "67": "14",
            "76": "14"
        },
        "10": {
            "120": "5",
            "24": "5"
        },
        "2": {
            "155": "18",
            "165": "18",
            "46": "14"
        },
        "3": {
            "145": "18",
            "200": "18",
            "57": "18"
        },
        "4": {
            "182": "14",
            "209": "14",
            "227": "5"
        },
        "5": {
            "107": "1",
            "135": "1",
            "233": "1"
        },
        "6": {
            "241": "1",
            "35": "1",
            "6": "1"
        },
        "7": {
            "15": "1",
            "87": "1",
            "99": "1"
        },
        "8": {
            "175": "14",
            "218": "14"
        }
    },
    "63": {
        "1": {
            "191": "19",
            "67": "19",
            "76": "19"
        },
        "10": {
            "120": "15",
            "24": "15"
        },
        "2": {
            "155": "15",
            "165": "15",
            "46": "15"
        },
        "3": {
            "145": "0",
            "200": "0",
            "57": "0"
        },
        "4": {
            "182": "15",
            "209": "15",
            "227": "15"
        },
        "5": {
            "107": "15",
            "135": "15",
            "233": "15"
        },
        "6": {
            "241": "0",
            "35": "0",
            "6": "0"
        },
        "7": {
            "15": "19",
            "87": "19",
            "99": "19"
        },
        "8": {
            "175": "0",
            "218": "0"
        }
    },
    "64": {
        "1": {
            "210": "11",
            "67": "11"
        },
        "10": {
            "120": "8",
            "24": "16",
            "47": "16"
        },
        "2": {
            "155": "9",
            "16": "9"
        },
        "3": {
            "145": "9",
            "200": "9",
            "57": "9"
        },
        "4": {
            "100": "16",
            "182": "16",
            "227": "16"
        },
        "5": {
            "107": "8",
            "76": "8"
        },
        "6": {
            "241": "11",
            "35": "11",
            "6": "11"
        },
        "7": {
            "166": "8",
            "234": "8",
            "87": "8"
        },
        "8": {
            "175": "16",
            "218": "16"
        },
        "9": {
            "136": "11",
            "192": "11"
        }
    },
    "65": {
        "1": {
            "210": "13",
            "67": "13"
        },
        "10": {
            "120": "6",
            "24": "6",
            "47": "6"
        },
        "2": {
            "155": "18",
            "16": "18"
        },
        "3": {
            "145": "6",
            "200": "14",
            "57": "6"
        },
        "4": {
            "100": "18",
            "182": "6",
            "227": "6"
        },
        "5": {
            "107": "14",
            "76": "14"
        },
        "6": {
            "241": "6",
            "35": "6",
            "6": "6"
        },
        "7": {
            "166": "14",
            "234": "14",
            "87": "14"
        },
        "8": {
            "175": "14",
            "218": "14"
        },
        "9": {
            "136": "18",
            "192": "18"
        }
    },
    "66": {
        "1": {
            "210": "19",
            "67": "19"
        },
        "10": {
            "120": "19",
            "24": "19",
            "47": "19"
        },
        "2": {
            "155": "0",
            "16": "0"
        },
        "3": {
            "145": "7",
            "200": "7",
            "57": "7"
        },
        "4": {
            "100": "7",
            "182": "7",
            "227": "7"
        },
        "5": {
            "107": "7",
            "76": "7"
        },
        "6": {
            "241": "0",
            "35": "0",
            "6": "0"
        },
        "7": {
            "166": "0",
            "234": "0",
            "87": "0"
        },
        "8": {
            "175": "7",
            "218": "7"
        },
        "9": {
            "136": "7",
            "192": "7"
        }
    },
    "67": {
        "1": {
            "146": "3",
            "210": "3",
            "67": "3"
        },
        "2": {
            "155": "15",
            "16": "17"
        },
        "3": {
            "108": "17",
            "121": "17",
            "57": "3"
        },
        "4": {
            "100": "17",
            "182": "12",
            "227": "12"
        },
        "5": {
            "25": "15",
            "48": "15",
            "76": "15"
        },
        "6": {
            "35": "3",
            "6": "3"
        },
        "7": {
            "166": "12",
            "234": "12",
            "87": "12"
        },
        "8": {
            "175": "12",
            "218": "12",
            "242": "12"
        },
        "9": {
            "136": "15",
            "192": "15",
            "201": "15"
        }
    },
    "68": {
        "1": {
            "146": "16",
            "210": "16",
            "67": "16"
        },
        "2": {
            "155": "14",
            "16": "2"
        },
        "3": {
            "108": "14",
            "121": "16",
            "57": "14"
        },
        "4": {
            "100": "6",
            "182": "6",
            "227": "6"
        },
        "5": {
            "25": "16",
            "48": "2",
            "76": "16"
        },
        "6": {
            "35": "2",
            "6": "2"
        },
        "7": {
            "166": "6",
            "234": "6",
            "87": "6"
        },
        "8": {
            "175": "14",
            "218": "14",
            "242": "14"
        },
        "9": {
            "136": "6",
            "192": "6",
            "201": "6"
        }
    },
    "69": {
        "1": {
            "146": "20",
            "210": "20",
            "67": "20"
        },
        "2": {
            "155": "10",
            "16": "10"
        },
        "3": {
            "108": "10",
            "121": "10",
            "57": "10"
        },
        "4": {
            "100": "10",
            "182": "10",
            "227": "10"
        },
        "5": {
            "25": "0",
            "48": "0",
            "76": "0"
        },
        "6": {
            "35": "20",
            "6": "20"
        },
        "7": {
            "166": "10",
            "234": "10",
            "87": "10"
        },
        "8": {
            "175": "0",
            "218": "0",
            "242": "0"
        },
        "9": {
            "136": "0",
            "192": "0",
            "201": "10"
        }
    },
    "70": {
        "1": {
            "146": "5",
            "228": "5",
            "67": "5"
        },
        "2": {
            "156": "1",
            "16": "19",
            "88": "1"
        },
        "3": {
            "109": "9",
            "121": "19",
            "58": "19"
        },
        "4": {
            "100": "1",
            "211": "19",
            "7": "1"
        },
        "5": {
            "25": "19",
            "48": "19",
            "76": "19"
        },
        "6": {
            "193": "9",
            "36": "9"
        },
        "7": {
            "166": "1",
            "183": "9",
            "219": "1"
        },
        "8": {
            "176": "5",
            "242": "1"
        },
        "9": {
            "136": "1",
            "201": "1",
            "235": "1"
        }
    },
    "71": {
        "1": {
            "146": "18",
            "228": "18",
            "67": "13"
        },
        "2": {
            "156": "11",
            "16": "18",
            "88": "18"
        },
        "3": {
            "109": "13",
            "121": "7",
            "58": "7"
        },
        "4": {
            "100": "13",
            "211": "7",
            "7": "13"
        },
        "5": {
            "25": "18",
            "48": "18",
            "76": "18"
        },
        "6": {
            "193": "7",
            "36": "7"
        },
        "7": {
            "166": "13",
            "183": "11",
            "219": "13"
        },
        "8": {
            "176": "11",
            "242": "11"
        },
        "9": {
            "136": "7",
            "201": "7",
            "235": "18"
        }
    },
    "72": {
        "1": {
            "146": "3",
            "228": "3",
            "67": "3"
        },
        "2": {
            "156": "3",
            "16": "6",
            "88": "3"
        },
        "3": {
            "109": "6",
            "121": "6",
            "58": "6"
        },
        "4": {
            "100": "6",
            "211": "6",
            "7": "6"
        },
        "5": {
            "25": "3",
            "48": "3",
            "76": "3"
        },
        "6": {
            "193": "6",
            "36": "6"
        },
        "7": {
            "166": "6",
            "183": "6",
            "219": "6"
        },
        "8": {
            "176": "3",
            "242": "3"
        },
        "9": {
            "136": "6",
            "201": "6",
            "235": "6"
        }
    },
    "73": {
        "1": {
            "146": "5",
            "228": "5",
            "68": "5"
        },
        "2": {
            "156": "19",
            "167": "19",
            "88": "8"
        },
        "3": {
            "109": "5",
            "58": "5"
        },
        "4": {
            "100": "8",
            "211": "19",
            "7": "8"
        },
        "5": {
            "25": "8",
            "48": "8"
        },
        "6": {
            "17": "8",
            "193": "8",
            "36": "8"
        },
        "7": {
            "137": "2",
            "183": "2",
            "219": "2"
        },
        "8": {
            "176": "19",
            "242": "19",
            "77": "2"
        },
        "9": {
            "122": "19",
            "201": "19",
            "235": "19"
        }
    },
    "74": {
        "1": {
            "146": "15",
            "228": "15",
            "68": "16"
        },
        "2": {
            "156": "16",
            "167": "16",
            "88": "16"
        },
        "3": {
            "109": "13",
            "58": "0"
        },
        "4": {
            "100": "13",
            "211": "13",
            "7": "13"
        },
        "5": {
            "25": "16",
            "48": "16"
        },
        "6": {
            "17": "16",
            "193": "16",
            "36": "16"
        },
        "7": {
            "137": "15",
            "183": "13",
            "219": "15"
        },
        "8": {
            "176": "0",
            "242": "0",
            "77": "13"
        },
        "9": {
            "122": "15",
            "201": "15",
            "235": "15"
        }
    },
    "75": {
        "1": {
            "146": "12",
            "228": "12",
            "68": "12"
        },
        "2": {
            "156": "20",
            "167": "20",
            "88": "20"
        },
        "3": {
            "109": "12",
            "58": "12"
        },
        "4": {
            "100": "12",
            "211": "12",
            "7": "12"
        },
        "5": {
            "25": "12",
            "48": "12"
        },
        "6": {
            "17": "20",
            "193": "20",
            "36": "20"
        },
        "7": {
            "137": "9",
            "183": "9",
            "219": "9"
        },
        "8": {
            "176": "9",
            "242": "9",
            "77": "9"
        },
        "9": {
            "122": "9",
            "201": "9",
            "235": "9"
        }
    },
    "76": {
        "1": {
            "147": "10",
            "228": "10",
            "68": "10"
        },
        "10": {
            "202": "14",
            "243": "14"
        },
        "2": {
            "156": "17",
            "167": "17"
        },
        "3": {
            "109": "14",
            "58": "14"
        },
        "4": {
            "123": "10",
            "211": "17",
            "7": "2"
        },
        "5": {
            "220": "17",
            "25": "17",
            "48": "17"
        },
        "6": {
            "17": "14",
            "193": "14",
            "36": "14"
        },
        "7": {
            "101": "10",
            "137": "2",
            "89": "2"
        },
        "8": {
            "176": "14",
            "77": "14"
        },
        "9": {
            "184": "14",
            "235": "14"
        }
    },
    "77": {
        "1": {
            "147": "8",
            "228": "8",
            "68": "3"
        },
        "10": {
            "202": "5",
            "243": "5"
        },
        "2": {
            "156": "16",
            "167": "16"
        },
        "3": {
            "109": "5",
            "58": "5"
        },
        "4": {
            "123": "5",
            "211": "5",
            "7": "5"
        },
        "5": {
            "220": "16",
            "25": "16",
            "48": "16"
        },
        "6": {
            "17": "16",
            "193": "16",
            "36": "16"
        },
        "7": {
            "101": "8",
            "137": "8",
            "89": "8"
        },
        "8": {
            "176": "8",
            "77": "8"
        },
        "9": {
            "184": "3",
            "235": "3"
        }
    },
    "78": {
        "1": {
            "147": "6",
            "228": "4",
            "68": "6"
        },
        "10": {
            "202": "6",
            "243": "6"
        },
        "2": {
            "156": "4",
            "167": "4"
        },
        "3": {
            "109": "6",
            "58": "6"
        },
        "4": {
            "123": "4",
            "211": "4",
            "7": "4"
        },
        "5": {
            "220": "6",
            "25": "4",
            "48": "4"
        },
        "6": {
            "17": "6",
            "193": "6",
            "36": "6"
        },
        "7": {
            "101": "6",
            "137": "6",
            "89": "6"
        },
        "8": {
            "176": "4",
            "77": "4"
        },
        "9": {
            "184": "4",
            "235": "4"
        }
    },
    "79": {
        "1": {
            "147": "2",
            "228": "2",
            "69": "2"
        },
        "10": {
            "202": "17",
            "243": "13",
            "8": "13"
        },
        "2": {
            "156": "7",
            "167": "2",
            "212": "7"
        },
        "3": {
            "124": "13"
        },
        "4": {
            "110": "7",
            "26": "7"
        },
        "5": {
            "220": "2",
            "48": "2"
        },
        "6": {
            "17": "17",
            "193": "7",
            "36": "7"
        },
        "7": {
            "101": "17",
            "137": "17",
            "89": "17"
        },
        "8": {
            "176": "13",
            "77": "13"
        },
        "9": {
            "184": "17",
            "235": "17",
            "59": "17"
        }
    },
    "80": {
        "1": {
            "147": "10",
            "228": "10",
            "69": "10"
        },
        "10": {
            "202": "10",
            "243": "10",
            "8": "10"
        },
        "2": {
            "156": "16",
            "167": "16",
            "212": "16"
        },
        "3": {
            "124": "10"
        },
        "4": {
            "110": "9",
            "26": "9"
        },
        "5": {
            "220": "16",
            "48": "3"
        },
        "6": {
            "17": "16",
            "193": "16",
            "36": "16"
        },
        "7": {
            "101": "9",
            "137": "9",
            "89": "9"
        },
        "8": {
            "176": "9",
            "77": "9"
        },
        "9": {
            "184": "3",
            "235": "3",
            "59": "3"
        }
    },
    "81": {
        "1": {
            "147": "20",
            "228": "20",
            "69": "20"
        },
        "10": {
            "202": "1",
            "243": "1",
            "8": "1"
        },
        "2": {
            "156": "1",
            "167": "1",
            "212": "1"
        },
        "3": {
            "124": "1"
        },
        "4": {
            "110": "20",
            "26": "20"
        },
        "5": {
            "220": "20",
            "48": "20"
        },
        "6": {
            "17": "20",
            "193": "20",
            "36": "20"
        },
        "7": {
            "101": "0",
            "137": "0",
            "89": "0"
        },
        "8": {
            "176": "20",
            "77": "20"
        },
        "9": {
            "184": "1",
            "235": "1",
            "59": "1"
        }
    },
    "82": {
        "1": {
            "228": "5",
            "69": "18",
            "78": "18"
        },
        "10": {
            "202": "5",
            "243": "5",
            "8": "5"
        },
        "2": {
            "156": "18",
            "212": "18"
        },
        "3": {
            "125": "5",
            "138": "5"
        },
        "4": {
            "111": "4",
            "26": "4",
            "49": "4"
        },
        "5": {
            "148": "6",
            "168": "6",
            "220": "6"
        },
        "6": {
            "17": "6",
            "193": "6"
        },
        "7": {
            "101": "6",
            "236": "6",
            "89": "6"
        },
        "8": {
            "176": "4"
        },
        "9": {
            "184": "4",
            "37": "4",
            "59": "18"
        }
    },
    "83": {
        "1": {
            "228": "10",
            "69": "7",
            "78": "7"
        },
        "10": {
            "202": "10",
            "243": "10",
            "8": "10"
        },
        "2": {
            "156": "7",
            "212": "7"
        },
        "3": {
            "125": "17",
            "138": "7"
        },
        "4": {
            "111": "10",
            "26": "10",
            "49": "10"
        },
        "5": {
            "148": "17",
            "168": "9",
            "220": "9"
        },
        "6": {
            "17": "9",
            "193": "9"
        },
        "7": {
            "101": "9",
            "236": "9",
            "89": "9"
        },
        "8": {
            "176": "9"
        },
        "9": {
            "184": "17",
            "37": "17",
            "59": "17"
        }
    },
    "84": {
        "1": {
            "228": "20",
            "69": "20",
            "78": "20"
        },
        "10": {
            "202": "20",
            "243": "20",
            "8": "20"
        },
        "2": {
            "156": "11",
            "212": "11"
        },
        "3": {
            "125": "0",
            "138": "0"
        },
        "4": {
            "111": "0",
            "26": "0",
            "49": "0"
        },
        "5": {
            "148": "11",
            "168": "11",
            "220": "11"
        },
        "6": {
            "17": "20",
            "193": "20"
        },
        "7": {
            "101": "11",
            "236": "11",
            "89": "11"
        },
        "8": {
            "176": "0"
        },
        "9": {
            "184": "20",
            "37": "20",
            "59": "20"
        }
    },
    "_comments": "Cost: 7211.253624\n\"cc0\": 55.000000, \"cc1\": 404.000000, \"cc2\": 70.000000, \"cc3\": 260.000000, \"cc4\": 1603.000000, \"cc5\": 640.000000, \"cc6\": 845.000000, \"cc7\": 34.400120, \"cc8\": 584.133309, \"cc9\": 1916.000000, \"cc10\": 411.272201, \"cc11\": 388.447993, Sum of cost components7211.253624 Time: 92.767255s\n"
}